pyjTable/__init__.py
pyjTable/column.py
pyjTable/jtable.py
pyjTable/UNKNOWN.egg-info/dependency_links.txt
pyjTable/UNKNOWN.egg-info/PKG-INFO
pyjTable/UNKNOWN.egg-info/SOURCES.txt
pyjTable/UNKNOWN.egg-info/top_level.txt
pyjtable-0.1.2.dist-info/WHEEL
pyjtable-0.1.2.dist-info/METADATA
pyjtable-0.1.2.dist-info/RECORD
