Metadata-Version: 2.1
Name: pyjtable
Version: 0.1.2
Summary: A python+sqlalchemy interface to generate javascript setup for for http://www.jtable.org/ tables.
License: MIT
Keywords: jTable
Author: Derek Wood
Requires-Python: >=3.7,<4.0
Classifier: 
Classifier: Environment :: Web Environment
Classifier: License :: OSI Approved :: MIT License
Classifier: Programming Language :: JavaScript
Classifier: Programming Language :: Python
Classifier: Programming Language :: Python :: 3
Classifier: Programming Language :: Python :: 3.7
Classifier: Programming Language :: Python :: 3.8
Classifier: Programming Language :: Python :: 3.9
Classifier: Topic :: Internet :: WWW/HTTP
Classifier: Topic :: Software Development :: Libraries :: Python Modules
Requires-Dist: SQLAlchemy (>=1.3,<2.0)
